winup/__init__.py
winup/net.py
winup/shell.py
winup/tasks.py
winup/animate/__init__.py
winup/animate/fx.py
winup/cli/__init__.py
winup/cli/main.py
winup/core/__init__.py
winup/core/component.py
winup/core/events.py
winup/core/hot_reload.py
winup/core/memoize.py
winup/core/network.py
winup/core/platform.py
winup/core/window.py
winup/data/__init__.py
winup/data/database.py
winup/data/firebase_connector.py
winup/data/mongo_connector.py
winup/data/mysql_connector.py
winup/data/postgres_connector.py
winup/data/sqlite_connector.py
winup/effects/__init__.py
winup/router/__init__.py
winup/router/router.py
winup/state/__init__.py
winup/state/manager.py
winup/style/__init__.py
winup/style/styler.py
winup/style/tailwind.py
winup/style/theming.py
winup/tools/__init__.py
winup/tools/camera.py
winup/tools/filesystem.py
winup/tools/notifications.py
winup/tools/profiler.py
winup/tools/wintools.py
winup/traits/__init__.py
winup/traits/base.py
winup/traits/context_menu.py
winup/traits/dnd.py
winup/traits/effects.py
winup/traits/tooltip.py
winup/ui/__init__.py
winup/ui/dialogs.py
winup/ui/layout_managers.py
winup/ui/layouts.py
winup/ui/utils.py
winup/ui/widget_factory.py
winup/ui/widgets/button.py
winup/ui/widgets/calendar.py
winup/ui/widgets/carousel.py
winup/ui/widgets/checkbox.py
winup/ui/widgets/color_picker.py
winup/ui/widgets/combobox.py
winup/ui/widgets/deck.py
winup/ui/widgets/dock.py
winup/ui/widgets/expandable_panel.py
winup/ui/widgets/frame.py
winup/ui/widgets/image.py
winup/ui/widgets/input.py
winup/ui/widgets/label.py
winup/ui/widgets/link.py
winup/ui/widgets/list.py
winup/ui/widgets/progress_bar.py
winup/ui/widgets/radio_button.py
winup/ui/widgets/rich_text.py
winup/ui/widgets/scroll_view.py
winup/ui/widgets/slider.py
winup/ui/widgets/switch.py
winup/ui/widgets/tabview.py
winup/ui/widgets/textarea.py
winup/ui/widgets/tree_view.py
winup/ui/widgets/graphs/__init__.py
winup/ui/widgets/graphs/bar_chart.py
winup/ui/widgets/graphs/line_chart.py
winup-2.6.7.dist-info/licenses/LICENSE
winup-2.6.7.dist-info/METADATA
winup-2.6.7.dist-info/WHEEL
winup-2.6.7.dist-info/entry_points.txt
winup-2.6.7.dist-info/top_level.txt
winup-2.6.7.dist-info/RECORD
