Metadata-Version: 2.4
Name: winup
Version: 2.6.7
Summary: A powerful, .exe Desktop and Web Application Python GUI framework built on top of PySide6.
Author-email: ebaadwaheed <ebaadalt@gmail.com>
License: MIT
Project-URL: Homepage, https://github.com/mebaadwaheed/winup
Project-URL: Documentation, https://github.com/mebaadwaheed/winup/wiki
Project-URL: Source, https://github.com/mebaadwaheed/winup
Project-URL: Issues, https://github.com/mebaadwaheed/winup/issues
Requires-Python: >=3.9
License-File: LICENSE
Requires-Dist: PySide6>=6.6.0
Requires-Dist: watchdog
Requires-Dist: click
Requires-Dist: questionary
Requires-Dist: websockets
Requires-Dist: pyinstaller
Provides-Extra: web
Requires-Dist: fastapi; extra == "web"
Requires-Dist: uvicorn[standard]; extra == "web"
Requires-Dist: python-multipart; extra == "web"
Requires-Dist: Jinja2; extra == "web"
Provides-Extra: camera
Requires-Dist: numpy; extra == "camera"
Requires-Dist: opencv-python; extra == "camera"
Provides-Extra: database
Requires-Dist: pymysql; extra == "database"
Requires-Dist: psycopg2-binary; extra == "database"
Requires-Dist: pymongo; extra == "database"
Requires-Dist: firebase-admin; extra == "database"
Dynamic: license-file
